pyciscospa/__init__.py
pyciscospa/__main__.py
pyciscospa/client.py
pyciscospa-0.1.4.dist-info/top_level.txt
pyciscospa-0.1.4.dist-info/METADATA
pyciscospa-0.1.4.dist-info/DESCRIPTION.rst
pyciscospa-0.1.4.dist-info/metadata.json
pyciscospa-0.1.4.dist-info/WHEEL
pyciscospa-0.1.4.dist-info/RECORD
