Metadata-Version: 2.0
Name: pyciscospa
Version: 0.1.4
Summary: A package to interface with Cisco SPA ATA devices
Home-page: https://github.com/davejcameron/pyciscospa
Author: David Cameron
Author-email: dave.j.cameron+pip@gmail.com
License: Apache Software License 2.0
Keywords: cisco ata
Platform: UNKNOWN
Classifier: Development Status :: 3 - Alpha
Classifier: Intended Audience :: Developers
Classifier: License :: OSI Approved :: Apache Software License
Classifier: Programming Language :: Python :: 2
Classifier: Programming Language :: Python :: 2.7
Classifier: Programming Language :: Python :: 3
Classifier: Programming Language :: Python :: 3.3
Classifier: Programming Language :: Python :: 3.4
Classifier: Programming Language :: Python :: 3.5
Classifier: Programming Language :: Python :: 3.6
Requires-Dist: requests
Requires-Dist: xmljson
Provides-Extra: dev
Requires-Dist: check-manifest; extra == 'dev'
Requires-Dist: requests-mock; extra == 'dev'
